{
    "version": 2,
    "styles": {
        "spacing": {
            "margin": {
                "right": "24px",
                "left": "24px"
            }
        }
    },
    "settings": {
        "typography": {
            "fluid": true,
            "fontFamilies": [
                {
                    "fontFace": [
                        {
                            "fontFamily": "Montserrat",
                            "fontStretch": "normal",
                            "fontStyle": "normal",
                            "fontWeight": "300 900",
                            "src": [
                                "file:./assets/fonts/Montserrat/Montserrat-VariableFont_wght.woff2"
                            ]
                        }
                    ],
                    "fontFamily": "\"Montserrat\", sans-serif",
                    "name": "Montserrat",
                    "slug": "body"
                }
            ]
        },

        "layout": {
            "contentSize": "840px"
        }
    }
}
